bkr/__init__.py
bkr/log.py
bkr/common/__init__.py
bkr/common/bexceptions.py
bkr/common/default.conf
bkr/common/helpers.py
bkr/common/helpers_six.py
bkr/common/hub.py
bkr/common/pyconfig.py
bkr/common/test_helpers.py
bkr/common/test_schema.py
bkr/common/test_xmlrpc.py
bkr/common/xmlrpc2.py
bkr/common/xmlrpc3.py
bkr/common/schema/beaker-inventory.ttl
bkr/common/schema/beaker-job.rnc
bkr/common/schema/beaker-job.rng
bkr/common/schema/beaker-task.rnc
bkr/common/schema/beaker-task.rng
beaker_common-29.2.dist-info/METADATA
beaker_common-29.2.dist-info/WHEEL
beaker_common-29.2.dist-info/top_level.txt
beaker_common-29.2.dist-info/RECORD
